gazu/__init__.py
gazu/__version__.py
gazu/asset.py
gazu/cache.py
gazu/casting.py
gazu/client.py
gazu/concept.py
gazu/context.py
gazu/edit.py
gazu/encoder.py
gazu/entity.py
gazu/events.py
gazu/exception.py
gazu/files.py
gazu/helpers.py
gazu/person.py
gazu/playlist.py
gazu/project.py
gazu/py.typed
gazu/scene.py
gazu/search.py
gazu/shot.py
gazu/sorting.py
gazu/sync.py
gazu/task.py
gazu/user.py
gazu-1.1.1.dist-info/licenses/LICENSE
gazu-1.1.1.dist-info/METADATA
gazu-1.1.1.dist-info/WHEEL
gazu-1.1.1.dist-info/top_level.txt
gazu-1.1.1.dist-info/RECORD
