Metadata-Version: 2.4
Name: gazu
Version: 1.1.1
Summary: Gazu is a client for Zou, the API to store the data of your CG production.
Home-page: https://gazu.cg-wire.com/
Author: CG Wire
Author-email: frank@cg-wire.com
License: GNU Library or Lesser General Public License (LGPL)
Keywords: cg,production,asset manager,asset,shot,tasks,tracking
Classifier: Development Status :: 5 - Production/Stable
Classifier: Environment :: Web Environment
Classifier: Framework :: Flask
Classifier: Intended Audience :: Developers
Classifier: Natural Language :: English
Classifier: Programming Language :: Python :: 3.7
Classifier: Programming Language :: Python :: 3.8
Classifier: Programming Language :: Python :: 3.9
Classifier: Programming Language :: Python :: 3.10
Classifier: Programming Language :: Python :: 3.11
Classifier: Programming Language :: Python :: 3.12
Classifier: Programming Language :: Python :: 3.13
Classifier: Programming Language :: Python :: 3.14
Classifier: Programming Language :: Python :: Implementation :: CPython
Classifier: Programming Language :: Python :: Implementation :: PyPy
Classifier: Topic :: Multimedia :: Graphics
Requires-Python: >= 3.7
License-File: LICENSE
Requires-Dist: python-socketio[client]<6,>=5.11.0
Requires-Dist: requests>=2.25.1
Requires-Dist: Deprecated==1.3.1
Requires-Dist: pywin32>=308; sys_platform == "win32"
Requires-Dist: typing_extensions==4.7.1
Provides-Extra: dev
Requires-Dist: wheel; extra == "dev"
Provides-Extra: test
Requires-Dist: pytest; extra == "test"
Requires-Dist: pytest-cov; extra == "test"
Requires-Dist: requests_mock; extra == "test"
Requires-Dist: multipart; python_version >= "3.13" and extra == "test"
Provides-Extra: lint
Requires-Dist: autoflake==2.3.1; python_version >= "3.8" and extra == "lint"
Requires-Dist: black==25.12.0; python_version >= "3.10" and extra == "lint"
Requires-Dist: pre-commit==4.5.1; python_version >= "3.10" and extra == "lint"
Dynamic: license-file
Dynamic: requires-python
